pdm_buildasset/__init__.py
pdm_buildasset/buildassets.py
pdm_buildasset/command.py
pdm_buildasset/hook.py
pdm_buildasset-1.0.0.dist-info/entry_points.txt
pdm_buildasset-1.0.0.dist-info/WHEEL
pdm_buildasset-1.0.0.dist-info/METADATA
pdm_buildasset-1.0.0.dist-info/licenses/LICENSE
pdm_buildasset-1.0.0.dist-info/RECORD
