Metadata-Version: 2.1
Name: pdm-buildasset
Version: 1.0.0
Summary: A PDM plugin to build external assets such as a react UI.
License: MIT
Author-email: Samuel Taylor <samtaylor.uk@gmail.com>
Requires-Python: >=3.10
Classifier: Development Status :: 3 - Alpha
Classifier: Programming Language :: Python :: 3
Classifier: Programming Language :: Python :: 3.10
Requires-Dist: pynsist>=2.8
Project-URL: Homepage, https://github.com/samtayuk/pdm-buildasset
Project-URL: Repository, https://github.com/samtayuk/pdm-buildasset
